{
  "generated": "2026-06-28T08:19:04Z",
  "global_score": 4.72,
  "articles_scored": 99,
  "words_matched": 311,
  "top_negative": [
    {
      "word": "perra",
      "score": -5
    },
    {
      "word": "fraude",
      "score": -4
    },
    {
      "word": "culo",
      "score": -4
    },
    {
      "word": "catástrofe",
      "score": -3
    },
    {
      "word": "destrucción",
      "score": -3
    },
    {
      "word": "locos",
      "score": -3
    },
    {
      "word": "crueldad",
      "score": -3
    },
    {
      "word": "peor",
      "score": -3
    }
  ],
  "top_positive": [
    {
      "word": "triunfo",
      "score": 4
    },
    {
      "word": "ganar",
      "score": 4
    },
    {
      "word": "amor",
      "score": 3
    },
    {
      "word": "feliz",
      "score": 3
    },
    {
      "word": "suerte",
      "score": 3
    },
    {
      "word": "bueno",
      "score": 3
    },
    {
      "word": "bondad",
      "score": 3
    },
    {
      "word": "popular",
      "score": 3
    }
  ],
  "per_source": {
    "El País": 3.98,
    "elDiario.es": 5.04,
    "El Mundo": 4.27,
    "ABC": 4.66,
    "El Confidencial": 4.72,
    "BBC Mundo": 5.03,
    "France 24 ES": 4.78,
    "La Nación AR": 4.63,
    "La Jornada MX": 4.75,
    "Desinformémonos": 4.52,
    "Resumen Latinoam.": 5.27
  },
  "articles": [
    {
      "source": "El País",
      "title": "Venezuela afronta la catástrofe con el Estado sobrepasado",
      "score": 2.6,
      "words": [
        {
          "word": "catástrofe",
          "score": -3
        }
      ]
    },
    {
      "source": "El País",
      "title": "Mapas del terremoto en Venezuela: las imágenes satélite confirman un reguero de ",
      "score": 4.47,
      "words": [
        {
          "word": "mayor",
          "score": 3
        },
        {
          "word": "destrucción",
          "score": -3
        },
        {
          "word": "falla",
          "score": -2
        }
      ]
    },
    {
      "source": "El País",
      "title": "Miriam Nogueras: “Sánchez tiene que irse o regalará el Gobierno a la extrema der",
      "score": 6.6,
      "words": [
        {
          "word": "cumplir",
          "score": 2
        }
      ]
    },
    {
      "source": "El País",
      "title": "La posición de Junts agrava el bloqueo parlamentario",
      "score": 3.8,
      "words": [
        {
          "word": "agrava",
          "score": -2
        },
        {
          "word": "bloqueo",
          "score": -1
        }
      ]
    },
    {
      "source": "El País",
      "title": "Austria es el rival de España en dieciseisavos tras un empate de locos contra Ar",
      "score": 2.6,
      "words": [
        {
          "word": "locos",
          "score": -3
        }
      ]
    },
    {
      "source": "El País",
      "title": "Solo las paradas de Diogo Costa frenan a una Colombia desatada ante la decepcion",
      "score": 4.4,
      "words": [
        {
          "word": "solo",
          "score": -2
        },
        {
          "word": "paradas",
          "score": -1
        },
        {
          "word": "decepcionante",
          "score": -2
        },
        {
          "word": "logra",
          "score": 2
        }
      ]
    },
    {
      "source": "El País",
      "title": "La Argentina B también necesita a Leo Messi para rendir a Jordania",
      "score": 3.4,
      "words": [
        {
          "word": "sentencia",
          "score": -2
        }
      ]
    },
    {
      "source": "elDiario.es",
      "title": "Los audios del Comité Federal: Page pide no tener miedo \"a ir a elecciones\" y Sá",
      "score": 5.35,
      "words": [
        {
          "word": "miedo",
          "score": -2
        },
        {
          "word": "ganar",
          "score": 4
        },
        {
          "word": "miedo",
          "score": -2
        },
        {
          "word": "apoyo",
          "score": 2
        },
        {
          "word": "mancha",
          "score": 2
        }
      ]
    },
    {
      "source": "elDiario.es",
      "title": "Pedro Sánchez, ante el Comité Federal del PSOE: \"Limpiaremos lo que haya que lim",
      "score": 5.33,
      "words": [
        {
          "word": "limpiar",
          "score": 2
        },
        {
          "word": "limpiar",
          "score": 2
        },
        {
          "word": "peor",
          "score": -3
        },
        {
          "word": "esperanza",
          "score": 2
        },
        {
          "word": "advertir",
          "score": -2
        }
      ]
    },
    {
      "source": "elDiario.es",
      "title": "Sánchez entona el himno de la resistencia ante un PSOE que se conjura para libra",
      "score": 4.78,
      "words": [
        {
          "word": "batalla",
          "score": -1
        },
        {
          "word": "batalla",
          "score": -1
        },
        {
          "word": "apoyo",
          "score": 2
        },
        {
          "word": "críticos",
          "score": -2
        },
        {
          "word": "tipo",
          "score": 2
        }
      ]
    },
    {
      "source": "elDiario.es",
      "title": "Feijóo, en la rueda de ratón de la moción de censura",
      "score": 5.11,
      "words": [
        {
          "word": "amenaza",
          "score": -2
        },
        {
          "word": "logra",
          "score": 2
        },
        {
          "word": "apoyo",
          "score": 2
        },
        {
          "word": "confianza",
          "score": 1
        },
        {
          "word": "mayor",
          "score": 3
        }
      ]
    },
    {
      "source": "elDiario.es",
      "title": "Feijóo pide que Catalunya se convierta en la \"llave\" para echar a Sánchez de la ",
      "score": 6.05,
      "words": [
        {
          "word": "rico",
          "score": 2
        },
        {
          "word": "asegurado",
          "score": 2
        },
        {
          "word": "capaz",
          "score": 1
        },
        {
          "word": "asegurado",
          "score": 2
        },
        {
          "word": "responsable",
          "score": 2
        }
      ]
    },
    {
      "source": "elDiario.es",
      "title": "63.134 euros al año con un cursillo de 150 horas y un inglés \"básico\": los sueld",
      "score": 4.67,
      "words": [
        {
          "word": "responsable",
          "score": 2
        },
        {
          "word": "mejor",
          "score": 3
        },
        {
          "word": "pagado",
          "score": 2
        },
        {
          "word": "cobrar",
          "score": -2
        },
        {
          "word": "puesto",
          "score": -2
        }
      ]
    },
    {
      "source": "elDiario.es",
      "title": "La vida privada de Zapatero y qué falla en el sistema judicial",
      "score": 4.34,
      "words": [
        {
          "word": "falla",
          "score": -2
        },
        {
          "word": "falla",
          "score": -2
        },
        {
          "word": "culo",
          "score": -4
        },
        {
          "word": "culpable",
          "score": -3
        },
        {
          "word": "dudas",
          "score": -1
        }
      ]
    },
    {
      "source": "elDiario.es",
      "title": "Los críticos de Movimiento Sumar pactan la lista para defenestrar a Lara Hernánd",
      "score": 4.4,
      "words": [
        {
          "word": "críticos",
          "score": -2
        },
        {
          "word": "duda",
          "score": -1
        },
        {
          "word": "batalla",
          "score": -1
        },
        {
          "word": "críticos",
          "score": -2
        },
        {
          "word": "duda",
          "score": -1
        }
      ]
    }
  ],
  "history": [
    {
      "timestamp": "2026-06-07T03:36:25Z",
      "score": 4.82
    },
    {
      "timestamp": "2026-06-07T07:51:57Z",
      "score": 4.83
    },
    {
      "timestamp": "2026-06-07T10:26:22Z",
      "score": 4.56
    },
    {
      "timestamp": "2026-06-07T12:18:10Z",
      "score": 4.56
    },
    {
      "timestamp": "2026-06-07T14:49:28Z",
      "score": 4.78
    },
    {
      "timestamp": "2026-06-07T16:11:59Z",
      "score": 4.56
    },
    {
      "timestamp": "2026-06-07T18:01:25Z",
      "score": 4.52
    },
    {
      "timestamp": "2026-06-07T20:08:44Z",
      "score": 4.65
    },
    {
      "timestamp": "2026-06-07T22:01:03Z",
      "score": 4.57
    },
    {
      "timestamp": "2026-06-08T00:03:54Z",
      "score": 4.57
    },
    {
      "timestamp": "2026-06-08T05:28:20Z",
      "score": 4.63
    },
    {
      "timestamp": "2026-06-08T10:47:30Z",
      "score": 4.86
    },
    {
      "timestamp": "2026-06-08T14:45:48Z",
      "score": 4.83
    },
    {
      "timestamp": "2026-06-08T17:49:49Z",
      "score": 4.81
    },
    {
      "timestamp": "2026-06-08T20:10:23Z",
      "score": 4.88
    },
    {
      "timestamp": "2026-06-08T22:23:59Z",
      "score": 4.66
    },
    {
      "timestamp": "2026-06-09T00:02:51Z",
      "score": 4.74
    },
    {
      "timestamp": "2026-06-09T05:02:45Z",
      "score": 4.77
    },
    {
      "timestamp": "2026-06-09T09:37:46Z",
      "score": 4.64
    },
    {
      "timestamp": "2026-06-09T12:34:05Z",
      "score": 4.58
    },
    {
      "timestamp": "2026-06-09T15:52:23Z",
      "score": 4.88
    },
    {
      "timestamp": "2026-06-09T18:00:19Z",
      "score": 4.78
    },
    {
      "timestamp": "2026-06-09T20:54:15Z",
      "score": 4.7
    },
    {
      "timestamp": "2026-06-09T22:21:46Z",
      "score": 4.85
    },
    {
      "timestamp": "2026-06-10T00:10:07Z",
      "score": 4.69
    },
    {
      "timestamp": "2026-06-10T05:14:47Z",
      "score": 4.7
    },
    {
      "timestamp": "2026-06-10T09:53:52Z",
      "score": 4.66
    },
    {
      "timestamp": "2026-06-10T12:54:09Z",
      "score": 4.66
    },
    {
      "timestamp": "2026-06-10T16:33:32Z",
      "score": 4.62
    },
    {
      "timestamp": "2026-06-10T19:32:26Z",
      "score": 4.57
    },
    {
      "timestamp": "2026-06-10T21:58:32Z",
      "score": 4.62
    },
    {
      "timestamp": "2026-06-10T23:39:50Z",
      "score": 4.72
    },
    {
      "timestamp": "2026-06-11T03:40:00Z",
      "score": 4.65
    },
    {
      "timestamp": "2026-06-11T08:43:54Z",
      "score": 4.75
    },
    {
      "timestamp": "2026-06-11T12:43:04Z",
      "score": 4.77
    },
    {
      "timestamp": "2026-06-11T16:52:09Z",
      "score": 4.73
    },
    {
      "timestamp": "2026-06-11T19:33:35Z",
      "score": 4.69
    },
    {
      "timestamp": "2026-06-11T22:00:10Z",
      "score": 4.81
    },
    {
      "timestamp": "2026-06-11T23:45:56Z",
      "score": 4.73
    },
    {
      "timestamp": "2026-06-12T03:39:22Z",
      "score": 4.86
    },
    {
      "timestamp": "2026-06-12T08:23:10Z",
      "score": 4.93
    },
    {
      "timestamp": "2026-06-12T12:16:48Z",
      "score": 4.87
    },
    {
      "timestamp": "2026-06-12T16:15:43Z",
      "score": 4.9
    },
    {
      "timestamp": "2026-06-12T19:02:48Z",
      "score": 4.95
    },
    {
      "timestamp": "2026-06-12T21:41:20Z",
      "score": 4.79
    },
    {
      "timestamp": "2026-06-12T23:14:58Z",
      "score": 4.78
    },
    {
      "timestamp": "2026-06-13T03:27:30Z",
      "score": 4.74
    },
    {
      "timestamp": "2026-06-13T07:43:35Z",
      "score": 4.87
    },
    {
      "timestamp": "2026-06-13T10:25:57Z",
      "score": 4.93
    },
    {
      "timestamp": "2026-06-13T12:23:29Z",
      "score": 5.03
    },
    {
      "timestamp": "2026-06-13T14:58:22Z",
      "score": 4.83
    },
    {
      "timestamp": "2026-06-13T16:18:55Z",
      "score": 4.89
    },
    {
      "timestamp": "2026-06-13T18:05:16Z",
      "score": 4.93
    },
    {
      "timestamp": "2026-06-13T20:13:47Z",
      "score": 4.82
    },
    {
      "timestamp": "2026-06-13T22:01:12Z",
      "score": 4.84
    },
    {
      "timestamp": "2026-06-14T00:03:51Z",
      "score": 4.83
    },
    {
      "timestamp": "2026-06-14T05:46:29Z",
      "score": 4.87
    },
    {
      "timestamp": "2026-06-14T09:29:40Z",
      "score": 4.81
    },
    {
      "timestamp": "2026-06-14T11:55:10Z",
      "score": 4.78
    },
    {
      "timestamp": "2026-06-14T13:56:50Z",
      "score": 4.72
    },
    {
      "timestamp": "2026-06-14T15:48:48Z",
      "score": 4.78
    },
    {
      "timestamp": "2026-06-14T17:18:05Z",
      "score": 4.77
    },
    {
      "timestamp": "2026-06-14T19:21:56Z",
      "score": 4.67
    },
    {
      "timestamp": "2026-06-14T21:08:25Z",
      "score": 4.68
    },
    {
      "timestamp": "2026-06-14T23:06:20Z",
      "score": 4.84
    },
    {
      "timestamp": "2026-06-15T03:58:16Z",
      "score": 4.86
    },
    {
      "timestamp": "2026-06-15T10:27:38Z",
      "score": 4.79
    },
    {
      "timestamp": "2026-06-15T16:15:40Z",
      "score": 4.57
    },
    {
      "timestamp": "2026-06-15T20:22:59Z",
      "score": 4.77
    },
    {
      "timestamp": "2026-06-15T23:00:42Z",
      "score": 4.81
    },
    {
      "timestamp": "2026-06-16T03:47:12Z",
      "score": 4.77
    },
    {
      "timestamp": "2026-06-16T09:23:34Z",
      "score": 4.77
    },
    {
      "timestamp": "2026-06-16T15:01:20Z",
      "score": 4.65
    },
    {
      "timestamp": "2026-06-16T19:30:51Z",
      "score": 4.73
    },
    {
      "timestamp": "2026-06-16T22:08:30Z",
      "score": 4.74
    },
    {
      "timestamp": "2026-06-17T00:13:29Z",
      "score": 4.61
    },
    {
      "timestamp": "2026-06-17T06:07:18Z",
      "score": 4.94
    },
    {
      "timestamp": "2026-06-17T11:44:15Z",
      "score": 4.89
    },
    {
      "timestamp": "2026-06-17T15:19:52Z",
      "score": 4.91
    },
    {
      "timestamp": "2026-06-17T18:12:29Z",
      "score": 4.92
    },
    {
      "timestamp": "2026-06-17T21:02:55Z",
      "score": 4.76
    },
    {
      "timestamp": "2026-06-17T23:21:09Z",
      "score": 4.83
    },
    {
      "timestamp": "2026-06-18T03:38:35Z",
      "score": 4.8
    },
    {
      "timestamp": "2026-06-18T08:43:08Z",
      "score": 4.72
    },
    {
      "timestamp": "2026-06-18T12:22:26Z",
      "score": 4.9
    },
    {
      "timestamp": "2026-06-18T16:27:43Z",
      "score": 4.8
    },
    {
      "timestamp": "2026-06-18T19:25:09Z",
      "score": 4.75
    },
    {
      "timestamp": "2026-06-18T22:04:39Z",
      "score": 4.93
    },
    {
      "timestamp": "2026-06-19T00:23:53Z",
      "score": 4.75
    },
    {
      "timestamp": "2026-06-19T06:15:02Z",
      "score": 4.83
    },
    {
      "timestamp": "2026-06-19T11:19:24Z",
      "score": 4.76
    },
    {
      "timestamp": "2026-06-19T14:58:11Z",
      "score": 4.66
    },
    {
      "timestamp": "2026-06-19T17:21:08Z",
      "score": 4.51
    },
    {
      "timestamp": "2026-06-19T19:45:42Z",
      "score": 4.47
    },
    {
      "timestamp": "2026-06-19T21:07:35Z",
      "score": 4.41
    },
    {
      "timestamp": "2026-06-19T22:53:43Z",
      "score": 4.52
    },
    {
      "timestamp": "2026-06-20T00:07:02Z",
      "score": 4.53
    },
    {
      "timestamp": "2026-06-20T05:10:33Z",
      "score": 4.44
    },
    {
      "timestamp": "2026-06-20T08:50:54Z",
      "score": 4.4
    },
    {
      "timestamp": "2026-06-20T11:15:12Z",
      "score": 4.61
    },
    {
      "timestamp": "2026-06-20T13:56:05Z",
      "score": 4.55
    },
    {
      "timestamp": "2026-06-20T15:44:56Z",
      "score": 4.63
    },
    {
      "timestamp": "2026-06-20T17:23:22Z",
      "score": 4.71
    },
    {
      "timestamp": "2026-06-20T19:21:03Z",
      "score": 4.72
    },
    {
      "timestamp": "2026-06-20T21:14:29Z",
      "score": 4.71
    },
    {
      "timestamp": "2026-06-20T23:04:37Z",
      "score": 4.77
    },
    {
      "timestamp": "2026-06-21T03:54:02Z",
      "score": 4.65
    },
    {
      "timestamp": "2026-06-21T08:27:51Z",
      "score": 4.69
    },
    {
      "timestamp": "2026-06-21T11:43:40Z",
      "score": 4.65
    },
    {
      "timestamp": "2026-06-21T14:03:31Z",
      "score": 4.78
    },
    {
      "timestamp": "2026-06-21T16:28:10Z",
      "score": 4.73
    },
    {
      "timestamp": "2026-06-21T18:17:58Z",
      "score": 4.8
    },
    {
      "timestamp": "2026-06-21T20:22:25Z",
      "score": 4.76
    },
    {
      "timestamp": "2026-06-21T22:11:48Z",
      "score": 4.9
    },
    {
      "timestamp": "2026-06-22T00:08:34Z",
      "score": 4.93
    },
    {
      "timestamp": "2026-06-22T06:26:12Z",
      "score": 5.12
    },
    {
      "timestamp": "2026-06-22T12:47:18Z",
      "score": 4.99
    },
    {
      "timestamp": "2026-06-22T17:37:51Z",
      "score": 4.87
    },
    {
      "timestamp": "2026-06-22T20:42:53Z",
      "score": 4.83
    },
    {
      "timestamp": "2026-06-22T22:44:50Z",
      "score": 4.84
    },
    {
      "timestamp": "2026-06-23T00:02:45Z",
      "score": 4.6
    },
    {
      "timestamp": "2026-06-23T04:57:30Z",
      "score": 4.72
    },
    {
      "timestamp": "2026-06-23T08:30:41Z",
      "score": 4.71
    },
    {
      "timestamp": "2026-06-23T11:58:09Z",
      "score": 4.74
    },
    {
      "timestamp": "2026-06-23T15:12:08Z",
      "score": 4.67
    },
    {
      "timestamp": "2026-06-23T17:50:18Z",
      "score": 4.48
    },
    {
      "timestamp": "2026-06-23T19:58:24Z",
      "score": 4.59
    },
    {
      "timestamp": "2026-06-23T21:45:25Z",
      "score": 4.62
    },
    {
      "timestamp": "2026-06-23T23:06:33Z",
      "score": 4.61
    },
    {
      "timestamp": "2026-06-24T02:56:01Z",
      "score": 4.48
    },
    {
      "timestamp": "2026-06-24T06:48:47Z",
      "score": 4.76
    },
    {
      "timestamp": "2026-06-24T10:20:22Z",
      "score": 4.69
    },
    {
      "timestamp": "2026-06-24T13:19:53Z",
      "score": 5.02
    },
    {
      "timestamp": "2026-06-24T16:17:33Z",
      "score": 4.98
    },
    {
      "timestamp": "2026-06-24T18:49:12Z",
      "score": 4.88
    },
    {
      "timestamp": "2026-06-24T20:46:11Z",
      "score": 4.82
    },
    {
      "timestamp": "2026-06-24T22:14:12Z",
      "score": 4.8
    },
    {
      "timestamp": "2026-06-25T00:08:23Z",
      "score": 4.66
    },
    {
      "timestamp": "2026-06-25T05:02:20Z",
      "score": 4.66
    },
    {
      "timestamp": "2026-06-25T08:56:38Z",
      "score": 4.69
    },
    {
      "timestamp": "2026-06-25T11:40:17Z",
      "score": 4.76
    },
    {
      "timestamp": "2026-06-25T14:25:57Z",
      "score": 4.8
    },
    {
      "timestamp": "2026-06-25T17:10:02Z",
      "score": 4.82
    },
    {
      "timestamp": "2026-06-25T19:55:52Z",
      "score": 4.71
    },
    {
      "timestamp": "2026-06-25T21:41:06Z",
      "score": 4.72
    },
    {
      "timestamp": "2026-06-25T23:15:10Z",
      "score": 4.73
    },
    {
      "timestamp": "2026-06-26T03:25:23Z",
      "score": 4.68
    },
    {
      "timestamp": "2026-06-26T07:48:30Z",
      "score": 4.7
    },
    {
      "timestamp": "2026-06-26T10:48:21Z",
      "score": 4.72
    },
    {
      "timestamp": "2026-06-26T13:08:26Z",
      "score": 4.69
    },
    {
      "timestamp": "2026-06-26T16:13:22Z",
      "score": 4.85
    },
    {
      "timestamp": "2026-06-26T18:49:27Z",
      "score": 4.88
    },
    {
      "timestamp": "2026-06-26T20:44:28Z",
      "score": 4.87
    },
    {
      "timestamp": "2026-06-26T22:10:07Z",
      "score": 4.84
    },
    {
      "timestamp": "2026-06-27T00:03:44Z",
      "score": 4.91
    },
    {
      "timestamp": "2026-06-27T04:50:53Z",
      "score": 4.96
    },
    {
      "timestamp": "2026-06-27T07:47:01Z",
      "score": 4.76
    },
    {
      "timestamp": "2026-06-27T10:04:19Z",
      "score": 4.76
    },
    {
      "timestamp": "2026-06-27T12:07:17Z",
      "score": 4.76
    },
    {
      "timestamp": "2026-06-27T14:26:59Z",
      "score": 4.62
    },
    {
      "timestamp": "2026-06-27T16:02:29Z",
      "score": 4.79
    },
    {
      "timestamp": "2026-06-27T17:59:45Z",
      "score": 4.61
    },
    {
      "timestamp": "2026-06-27T19:40:32Z",
      "score": 4.69
    },
    {
      "timestamp": "2026-06-27T20:59:04Z",
      "score": 4.87
    },
    {
      "timestamp": "2026-06-27T22:10:15Z",
      "score": 4.86
    },
    {
      "timestamp": "2026-06-27T23:58:56Z",
      "score": 4.92
    },
    {
      "timestamp": "2026-06-28T04:39:36Z",
      "score": 4.87
    },
    {
      "timestamp": "2026-06-28T08:19:04Z",
      "score": 4.72
    }
  ]
}